[
  {
    "name": "redis4-0-struct-sds",
    "type": 10,
    "title": "Redis4.0源码解析--动态字符串SDS",
    "tags": "Redis 源码解析 SDS",
    "summary": "Redis官方在2016年12月发布了4.0-rc1版本，从此揭开了4.0版本的序幕，但到目前为止（2017年6月）还没有正式发布4.0版本提供给生产环境使用，笔者在2.8时代开始接触Redis，在做的几个项目中也都使用它作为缓存和数据交换的渠道，想着前辈们把3.0版本都源码解析的都差不多了，网上4.0版本解析却很少，所以和大家共同分享下Redis源码阅读的经历",
    "coverImage": "",
    "groupName": "Redis",
    "creator": "charpty",
    "creationDate": "2017-07-01 00:00:00",
    "modificationDate": "2017-07-01 00:00:00",
    "displayOrder": 100
  },
  {
    "name": "redis4-0-struct-list",
    "type": 10,
    "title": "Redis4.0源码解析--3种线性表",
    "tags": "Redis 源码解析 线性表",
    "summary": "上一章讲了SDS动态字符串，大概讲了看的方向，其实更深层次的还是要请读者自己看源码，我将源码加上了注释，这样大家看起来也更加的方便，本文讲Redis中的链表",
    "coverImage": "",
    "groupName": "Redis",
    "creator": "charpty",
    "creationDate": "2017-07-06 00:00:00",
    "modificationDate": "2017-07-06 00:00:00",
    "displayOrder": 100
  },
  {
    "name": "redis4-0-struct-dict",
    "type": 10,
    "title": "Redis4.0源码解析--字典",
    "tags": "Redis 源码解析 字典 哈希表",
    "summary": "",
    "coverImage": "",
    "groupName": "Redis",
    "creator": "charpty",
    "creationDate": "2017-10-03 00:00:00",
    "modificationDate": "2017-10-03 00:00:00",
    "displayOrder": 100
  }
]